qunetsim/__init__.py
qunetsim/backends/__init__.py
qunetsim/backends/backend.py
qunetsim/backends/cqc_backend.py
qunetsim/backends/eqsn_backend.py
qunetsim/backends/projectq_backend.py
qunetsim/backends/qutip_backend.py
qunetsim/backends/rw_lock.py
qunetsim/backends/safe_dict.py
qunetsim/components/__init__.py
qunetsim/components/host.py
qunetsim/components/network.py
qunetsim/components/protocols.py
qunetsim/objects/__init__.py
qunetsim/objects/daemon_thread.py
qunetsim/objects/logger.py
qunetsim/objects/message.py
qunetsim/objects/qubit.py
qunetsim/objects/connections/__init__.py
qunetsim/objects/connections/classical_connection.py
qunetsim/objects/connections/connection.py
qunetsim/objects/connections/quantum_connection.py
qunetsim/objects/connections/channel_models/__init__.py
qunetsim/objects/connections/channel_models/binary_erasure.py
qunetsim/objects/connections/channel_models/classical_model.py
qunetsim/objects/connections/channel_models/fibre.py
qunetsim/objects/packets/__init__.py
qunetsim/objects/packets/packet.py
qunetsim/objects/packets/routing_packet.py
qunetsim/objects/storage/__init__.py
qunetsim/objects/storage/classical_storage.py
qunetsim/objects/storage/quantum_storage.py
qunetsim/utils/__init__.py
qunetsim/utils/constants.py
qunetsim-0.1.3.post1.data/scripts/template
qunetsim-0.1.3.post1.dist-info/LICENSE
qunetsim-0.1.3.post1.dist-info/METADATA
qunetsim-0.1.3.post1.dist-info/WHEEL
qunetsim-0.1.3.post1.dist-info/top_level.txt
qunetsim-0.1.3.post1.dist-info/RECORD
