Metadata-Version: 2.1
Name: qunetsim
Version: 0.1.3.post1
Summary: A Quantum Network Simulation Framework
Home-page: https://github.com/tqsd/QuNetSim
Download-URL: https://github.com/tqsd/QuNetSim/releases/tag/0.1.2
Author: Stephen DiAdamo, Janis Nötzel, Benjamin Zanger, Mert Mehmet Bese
Author-email: stephen.diadamo@gmail.com
License: MIT
Keywords: quantum,networks,simulator,internet,QuNetSim
Classifier: Development Status :: 3 - Alpha
Classifier: Intended Audience :: Developers
Classifier: Topic :: Software Development :: Build Tools
Classifier: License :: OSI Approved :: MIT License
Classifier: Operating System :: OS Independent
Classifier: Programming Language :: Python :: 3
Classifier: Programming Language :: Python :: 3.6
Requires-Python: >=3.6
License-File: LICENSE
Requires-Dist: eqsn
Requires-Dist: networkx
Requires-Dist: numpy
Requires-Dist: scipy
Requires-Dist: matplotlib
Requires-Dist: pathvalidate
